pyathena_lite/__init__.py
pyathena_lite/connecter.py
pyathena_lite-0.1.0.dist-info/WHEEL
pyathena_lite-0.1.0.dist-info/METADATA
pyathena_lite-0.1.0.dist-info/RECORD
